instrumentcontrol/__init__.py
instrumentcontrol/instrumentcontrol.py
instrumentcontrol-0.1.40.dist-info/LICENSE
instrumentcontrol-0.1.40.dist-info/METADATA
instrumentcontrol-0.1.40.dist-info/WHEEL
instrumentcontrol-0.1.40.dist-info/top_level.txt
instrumentcontrol-0.1.40.dist-info/RECORD
