Metadata-Version: 2.1
Name: instrumentcontrol
Version: 0.1.40
Summary: Python Instrument Control for Load tuner and PA testing integration
Author-email: Grace Gomez <grace.gomez@colorado.edu>
Project-URL: Homepage, https://github.com/RFPAL-Github-Organization/LoadTuner-repo
Classifier: Programming Language :: Python :: 3
Classifier: License :: OSI Approved :: MIT License
Classifier: Operating System :: OS Independent
Requires-Python: >=3.8
License-File: LICENSE
